wagtailseo/__init__.py
wagtailseo/apps.py
wagtailseo/blocks.py
wagtailseo/models.py
wagtailseo/schema.py
wagtailseo/settings.py
wagtailseo/utils.py
wagtailseo/wagtail_hooks.py
wagtailseo/migrations/0001_initial.py
wagtailseo/migrations/0002_remove_seosettings_amp_pages.py
wagtailseo/migrations/__init__.py
wagtailseo/templates/wagtailseo/meta.html
wagtailseo/templates/wagtailseo/struct_data.html
wagtailseo/templates/wagtailseo/wagtailseo-line-chart.svg
cjkcms_seo-2.4.0.dist-info/LICENSE
cjkcms_seo-2.4.0.dist-info/METADATA
cjkcms_seo-2.4.0.dist-info/WHEEL
cjkcms_seo-2.4.0.dist-info/top_level.txt
cjkcms_seo-2.4.0.dist-info/RECORD
