Metadata-Version: 2.1
Name: cjkcms-seo
Version: 2.4.0
Summary: Search engine and social media optimization for Wagtail.
Home-page: https://github.com/cjkpl/cjkcms-seo.git
Author: Grzegorz Krol
Author-email: info@cjkcms.com
License: BSD license
Classifier: Framework :: Django
Classifier: Framework :: Wagtail
Classifier: Framework :: Wagtail :: 4
Classifier: Framework :: Wagtail :: 5
Classifier: Intended Audience :: Developers
Classifier: License :: OSI Approved :: BSD License
Classifier: Natural Language :: English
Classifier: Operating System :: OS Independent
Classifier: Programming Language :: Python :: 3
Classifier: Programming Language :: Python :: 3 :: Only
Classifier: Topic :: Internet :: WWW/HTTP :: Site Management
Requires-Python: >=3.8
License-File: LICENSE
Requires-Dist: wagtail <=6.0,>=4.0
